setup.cfg
setup.py
resqueue/__init__.py
resqueue/resqueue.py
resqueue.egg-info/PKG-INFO
resqueue.egg-info/SOURCES.txt
resqueue.egg-info/dependency_links.txt
resqueue.egg-info/top_level.txt