Metadata-Version: 1.1
Name: resqueue
Version: 0.0.17
Summary: job submission in python using job managers
Home-page: https://github.com/YSanchezAraujo/resqueue
Author: Yoel Sanchez Araujo
Author-email: yoelsanchez006@gmail.com
License: UNKNOWN
Download-URL: https://github.com/YSanchezAraujo/archive/0.0.17.tar.gz
Keywords: clusters,slurm
Platform: UNKNOWN
